README.rst
setup.py
NitPycker.egg-info/PKG-INFO
NitPycker.egg-info/SOURCES.txt
NitPycker.egg-info/dependency_links.txt
NitPycker.egg-info/entry_points.txt
NitPycker.egg-info/requires.txt
NitPycker.egg-info/top_level.txt
nitpycker/__init__.py
nitpycker/__main__.py
nitpycker/logger.py
nitpycker/result.py
nitpycker/runners.py
nitpycker/plugins/__init__.py
nitpycker/plugins/attribute_filter.py
nitpycker/plugins/coverage.py
nitpycker/plugins/manager.py
nitpycker/plugins/text_reporter.py
nitpycker/plugins/xunit.py