Metadata-Version: 1.1
Name: NitPycker
Version: 0.1
Summary: A multithreaded test runner
Home-page: https://github.com/BenjaminSchubert/NitPycker
Author: Benjamin Schubert
Author-email: ben.c.schubert@gmail.com
License: MIT
Download-URL: https://github.com/BenjaminSchubert/NitPycker/tar.gz/0.1
Platform: UNKNOWN
Classifier: Topic :: Software Development :: Testing
Classifier: Development Status :: 3 - Alpha
Classifier: Environment :: Console
Classifier: License :: OSI Approved :: MIT License
Classifier: Natural Language :: English
Classifier: Operating System :: Unix
Classifier: Programming Language :: Python :: 3.4
Classifier: Programming Language :: Python :: 3.5
